modern_treasury/__init__.py
modern_treasury/_base_client.py
modern_treasury/_client.py
modern_treasury/_compat.py
modern_treasury/_constants.py
modern_treasury/_exceptions.py
modern_treasury/_files.py
modern_treasury/_legacy_response.py
modern_treasury/_models.py
modern_treasury/_qs.py
modern_treasury/_resource.py
modern_treasury/_response.py
modern_treasury/_streaming.py
modern_treasury/_types.py
modern_treasury/_version.py
modern_treasury/pagination.py
modern_treasury/py.typed
modern_treasury/_utils/__init__.py
modern_treasury/_utils/_compat.py
modern_treasury/_utils/_datetime_parse.py
modern_treasury/_utils/_logs.py
modern_treasury/_utils/_proxy.py
modern_treasury/_utils/_reflection.py
modern_treasury/_utils/_resources_proxy.py
modern_treasury/_utils/_streams.py
modern_treasury/_utils/_sync.py
modern_treasury/_utils/_transform.py
modern_treasury/_utils/_typing.py
modern_treasury/_utils/_utils.py
modern_treasury/lib/.keep
modern_treasury/resources/__init__.py
modern_treasury/resources/account_collection_flows.py
modern_treasury/resources/account_details.py
modern_treasury/resources/bulk_requests.py
modern_treasury/resources/bulk_results.py
modern_treasury/resources/connection_legal_entities.py
modern_treasury/resources/connections.py
modern_treasury/resources/counterparties.py
modern_treasury/resources/documents.py
modern_treasury/resources/events.py
modern_treasury/resources/expected_payments.py
modern_treasury/resources/external_accounts.py
modern_treasury/resources/foreign_exchange_quotes.py
modern_treasury/resources/holds.py
modern_treasury/resources/incoming_payment_details.py
modern_treasury/resources/journal_entries.py
modern_treasury/resources/journal_reports.py
modern_treasury/resources/ledger_account_balance_monitors.py
modern_treasury/resources/ledger_account_categories.py
modern_treasury/resources/ledger_account_statements.py
modern_treasury/resources/ledger_accounts.py
modern_treasury/resources/ledger_entries.py
modern_treasury/resources/ledgers.py
modern_treasury-1.62.0.dist-info/METADATA
modern_treasury-1.62.0.dist-info/WHEEL
modern_treasury-1.62.0.dist-info/licenses/LICENSE
modern_treasury-1.62.0.dist-info/RECORD
